register_file.v
module register_file (
    input wire clk,
    input wire rst_n,

    // Read Interface
    input wire [2:0] read_addr,
    output reg [31:0] read_data,

    // Write Interface
    input wire [2:0] write_addr,
    input wire [31:0] write_data,
    input wire write_en
);

// 8 registers, each 32 bits wide
reg [31:0] registers [7:0];

// Read Logic
always @(posedge clk) begin
    if (~rst_n) begin
        read_data <= 32'b0;
    end else begin
        read_data <= registers[read_addr];
    end
end

// Write Logic
always @(posedge clk) begin
    if (write_en) begin
        registers[write_addr] <= write_data;
    end
end
endmodule

axi_slave.v
module axi_slave (
    input wire clk,
    input wire rst_n,

    // AXI4-Lite Write Address Channel
    input wire [31:0] awaddr,
    input wire awvalid,
    output reg awready,

    // AXI4-Lite Write Data Channel
    input wire [31:0] wdata,
    input wire [3:0] wstrb,
    input wire wvalid,
    output reg wready,

    // AXI4-Lite Write Response Channel
    output reg [1:0] bresp,
    output reg bvalid,
    input wire bready,

    // AXI4-Lite Read Address Channel
    input wire [31:0] araddr,
    input wire arvalid,
    output reg arready,

    // AXI4-Lite Read Data Channel
    output wire [31:0] rdata,
    output reg [1:0] rresp,
    output reg rvalid,
    input wire rready
);

// State machine for write transaction
localparam [1:0] IDLE = 2'b00, WRITE = 2'b01, WRITE_RESP = 2'b10;
reg [1:0] write_state;

// Internal wires for connecting to register_file
wire [2:0] write_reg_addr;
wire [2:0] read_reg_addr;

// Instantiate the register file
register_file u_register_file (
    .clk(clk),
    .rst_n(rst_n),
    .read_addr(read_reg_addr),
    .read_data(rdata),
    .write_addr(write_reg_addr),
    .write_data(wdata),
    .write_en(wvalid && wready) // Write enable signal
);

// --- WRITE CHANNEL LOGIC ---
assign write_reg_addr = awaddr[4:2]; // Use bits 4:2 for 8 registers

// FSM for write transactions
always @(posedge clk or negedge rst_n) begin
    if (~rst_n) begin
        write_state <= IDLE;
        awready <= 1'b0;
        wready <= 1'b0;
        bvalid <= 1'b0;
        bresp <= 2'b00;
    end else begin
        case (write_state)
            IDLE: begin
                awready <= 1'b1; // Always ready to accept a new address
                wready <= 1'b1;  // Always ready to accept new data
                if (awvalid && wvalid) begin // Handshake complete
                    write_state <= WRITE;
                end
            end
            WRITE: begin
                awready <= 1'b0;
                wready <= 1'b0;
                bvalid <= 1'b1; // Assert response valid
                bresp <= 2'b00; // OKAY response
                write_state <= WRITE_RESP;
            end
            WRITE_RESP: begin
                if (bready) begin // Master has accepted the response
                    bvalid <= 1'b0;
                    write_state <= IDLE;
                end
            end
        endcase
    end
end

// --- READ CHANNEL LOGIC ---
assign read_reg_addr = araddr[4:2];

// Read logic uses combinational and simple sequential logic
reg [1:0] read_state;
localparam [1:0] R_IDLE = 2'b00, R_READ = 2'b01;

always @(posedge clk or negedge rst_n) begin
    if (~rst_n) begin
        read_state <= R_IDLE;
        arready <= 1'b0;
        rvalid <= 1'b0;
        rresp <= 2'b00;
    end else begin
        case (read_state)
            R_IDLE: begin
                arready <= 1'b1; // Ready for a read address
                if (arvalid) begin
                    read_state <= R_READ;
                end
            end
            R_READ: begin
                arready <= 1'b0;
                rvalid <= 1'b1; // Assert read data is valid
                rresp <= 2'b00;
                if (rready) begin // Master has accepted data
                    rvalid <= 1'b0;
                    read_state <= R_IDLE;
                end
            end
        endcase
    end
end
endmodule

axi_slave_tb.sv
`timescale 1ns / 1ps

module axi_slave_tb;

// --- Signals ---
reg clk;
reg rst_n;

// AXI master signals (driven by testbench)
reg [31:0] awaddr;
reg awvalid;
reg [31:0] wdata;
reg [3:0] wstrb;
reg wvalid;
wire awready;
wire wready;
wire bvalid;
wire [1:0] bresp;

reg [31:0] araddr;
reg arvalid;
wire arready;
wire [31:0] rdata;
wire [1:0] rresp;
wire rvalid;
reg rready;

// --- Instantiate the slave ---
axi_slave u_axi_slave (
    .clk(clk),
    .rst_n(rst_n),
    .awaddr(awaddr),
    .awvalid(awvalid),
    .awready(awready),
    .wdata(wdata),
    .wstrb(wstrb),
    .wvalid(wvalid),
    .wready(wready),
    .bresp(bresp),
    .bvalid(bvalid),
    .bready(bready),
    .araddr(araddr),
    .arvalid(arvalid),
    .arready(arready),
    .rdata(rdata),
    .rresp(rresp),
    .rvalid(rvalid),
    .rready(rready)
);

// --- Clock Generation ---
initial begin
    clk = 0;
    forever #5 clk = ~clk; // 10 ns period
end

// --- Dump for GTKWave ---
initial begin
    $dumpfile("waves.vcd");
    $dumpvars(0, axi_slave_tb);
end

// --- Test Sequence ---
initial begin
    // 1. Initial Reset
    awvalid = 1'b0; wvalid = 1'b0; arvalid = 1'b0; rready = 1'b0;
    rst_n = 1'b0;
    #20;
    rst_n = 1'b1;
    #10;

    // 2. Write to register 0
    $display("Time %0t: Starting write transaction to reg 0.", $time);
    awaddr = 32'h00;
    wdata = 32'hdeadbeef;
    awvalid = 1'b1;
    wvalid = 1'b1;
    @(posedge clk);
    wait (awready && wready); // Wait for slave handshake
    awvalid = 1'b0;
    wvalid = 1'b0;
    wait (bvalid); // Wait for write response
    $display("Time %0t: Write transaction complete. Got response %b.", $time, bresp);
    #10;

    // 3. Read from register 0
    $display("Time %0t: Starting read transaction from reg 0.", $time);
    araddr = 32'h00;
    arvalid = 1'b1;
    @(posedge clk);
    wait (arready); // Wait for slave handshake
    arvalid = 1'b0;
    wait (rvalid); // Wait for read data
    if (rdata == 32'hdeadbeef) begin
        $display("Time %0t: Read transaction successful! Got data: %h", $time, rdata);
    end else begin
        $display("Time %0t: Read transaction failed! Got data: %h, expected: %h", $time, rdata, 32'hdeadbeef);
    end
    rready = 1'b1;
    @(posedge clk);
    rready = 1'b0;

    #20;
    $finish;
end
endmodule

waves.vcd
$date
	Sat Aug 16 10:42:16 2025
$end
$version
	Icarus Verilog
$end
$timescale
	1ps
$end
$scope module axi_slave_tb $end
$var wire 1 ! bready $end
$var wire 1 " wready $end
$var wire 1 # rvalid $end
$var wire 2 $ rresp [1:0] $end
$var wire 32 % rdata [31:0] $end
$var wire 1 & bvalid $end
$var wire 2 ' bresp [1:0] $end
$var wire 1 ( awready $end
$var wire 1 ) arready $end
$var reg 32 * araddr [31:0] $end
$var reg 1 + arvalid $end
$var reg 32 , awaddr [31:0] $end
$var reg 1 - awvalid $end
$var reg 1 . clk $end
$var reg 1 / rready $end
$var reg 1 0 rst_n $end
$var reg 32 1 wdata [31:0] $end
$var reg 4 2 wstrb [3:0] $end
$var reg 1 3 wvalid $end
$scope module u_axi_slave $end
$var wire 32 4 araddr [31:0] $end
$var wire 1 + arvalid $end
$var wire 32 5 awaddr [31:0] $end
$var wire 1 - awvalid $end
$var wire 1 ! bready $end
$var wire 1 . clk $end
$var wire 1 / rready $end
$var wire 1 0 rst_n $end
$var wire 32 6 wdata [31:0] $end
$var wire 4 7 wstrb [3:0] $end
$var wire 1 3 wvalid $end
$var wire 3 8 write_reg_addr [2:0] $end
$var wire 3 9 read_reg_addr [2:0] $end
$var wire 32 : rdata [31:0] $end
$var parameter 2 ; IDLE $end
$var parameter 2 < R_IDLE $end
$var parameter 2 = R_READ $end
$var parameter 2 > WRITE $end
$var parameter 2 ? WRITE_RESP $end
$var reg 1 ) arready $end
$var reg 1 ( awready $end
$var reg 2 @ bresp [1:0] $end
$var reg 1 & bvalid $end
$var reg 2 A read_state [1:0] $end
$var reg 2 B rresp [1:0] $end
$var reg 1 # rvalid $end
$var reg 1 " wready $end
$var reg 2 C write_state [1:0] $end
$scope module u_register_file $end
$var wire 1 . clk $end
$var wire 3 D read_addr [2:0] $end
$var wire 1 0 rst_n $end
$var wire 3 E write_addr [2:0] $end
$var wire 32 F write_data [31:0] $end
$var wire 1 G write_en $end
$var reg 32 H read_data [31:0] $end
$upscope $end
$upscope $end
$upscope $end
$enddefinitions $end
$comment Show the parameter values. $end
$dumpall
b10 ?
b1 >
b1 =
b0 <
b0 ;
$end
#0
$dumpvars
bx H
0G
bx F
bx E
bx D
b0 C
b0 B
b0 A
b0 @
bx :
bx 9
bx 8
bx 7
bx 6
bx 5
bx 4
03
bx 2
bx 1
00
0/
0.
0-
bx ,
0+
bx *
0)
0(
b0 '
0&
bx %
b0 $
0#
0"
z!
$end
#5000
b0 %
b0 :
b0 H
1.
#10000
0.
#15000
1.
#20000
0.
10
#25000
bx %
bx :
bx H
1)
1"
1(
1.
#30000
1G
b0 8
b0 E
0.
13
1-
b11011110101011011011111011101111 1
b11011110101011011011111011101111 6
b11011110101011011011111011101111 F
b0 ,
b0 5
#35000
b1 C
0G
03
0-
1.
#40000
0.
#45000
b10 C
1&
0"
0(
1.
#50000
0.
#55000
b11011110101011011011111011101111 %
b11011110101011011011111011101111 :
b11011110101011011011111011101111 H
b1 A
b0 9
b0 D
1.
0+
b0 *
b0 4
#60000
0.
#65000
1/
1#
0)
1.
#70000
0.
#75000
b0 A
0#
0/
1.
#80000
0.
#85000
1)
1.
